ardynamics_cli-1.1.1.dist-info/METADATA
ardynamics_cli-1.1.1.dist-info/RECORD
ardynamics_cli-1.1.1.dist-info/WHEEL
ardynamics_cli-1.1.1.dist-info/entry_points.txt
ardynamics_cli-1.1.1.dist-info/top_level.txt
cli/__init__.py
cli/__main__.py
cli/cli.py
cli/commands/__init__.py
cli/commands/backup.py
cli/commands/base.py
cli/commands/restore.py
cli/lib/__init__.py
cli/lib/config.py
cli/lib/domain.py
cli/lib/error.py
cli/lib/httpd.py
cli/lib/mariadb.py
cli/lib/php.py
cli/lib/ssm.py
cli/lib/user.py
