Metadata-Version: 2.1
Name: ardynamics-cli
Version: 1.1.1
Summary: AR Dynamics CLI
Home-page: https://ardynamics.eu
Author: Alwin Roosen
Author-email: info@alwinroosen.tech
License: UNLICENSE
Keywords: ardynamics-cli
Platform: UNKNOWN
Classifier: Intended Audience :: Developers
Classifier: Topic :: Utilities
Classifier: License :: Public Domain
Classifier: Natural Language :: English
Classifier: Operating System :: OS Independent
Classifier: Programming Language :: Python :: 2
Classifier: Programming Language :: Python :: 2.6
Classifier: Programming Language :: Python :: 2.7
Provides-Extra: test
Requires-Dist: docopt
Requires-Dist: boto3
Requires-Dist: mysql-connector-python
Provides-Extra: test
Requires-Dist: coverage; extra == 'test'
Requires-Dist: pytest; extra == 'test'
Requires-Dist: pytest-cov; extra == 'test'
